Workbook

Sheet Projects
A1: Project ID | B1: Project Name | C1: Status | D1: Start Date | E1: End Date | F1: Planned Budget | G1: Planned Revenue | H1: Sellable Area | I1: Units Count
A2: P001 | B2: Budva Residence | C2: Pause | D2: 46122 | E2: 46133 | F2: 8500000 | G2: 12000000 | H2: 3500 | I2: 42
A3: P002 | B3: Bar Residence | C3: Construction | D3: 46119 | E3: 46136 | F3: 129000 | G3: 1500000 | H3: 2000 | I3: 12
A4: P003 | B4: Ulcin Residence | C4: Construction | D4: 46022 | E4: 46473 | F4: 239000 | G4: 2323200 | H4: 3000 | I4: 14

Sheet Units
A1: Unit ID | B1: Project ID | C1: Type | D1: Number | E1: Floor | F1: Area | G1: Status
A2: U001 | B2: Budva Residence | C2: Apartment | D2: A-12 | E2: 1 | F2: 65 | G2: Available
A3: U002 | B3: Budva Residence | C3: Pakinkg | D3: A-13 | E3: 1 | F3: 4 | G3: Reserved
A4: U003 | B4: Budva Residence | C4: Apartment | D4: A-14 | E4: 3 | F4: 12 | G4: Sold
A5: U004 | B5: Ulcin Residence | C5: Apartment | D5: A-15 | E5: 5 | F5: 65 | G5: Sold
A6: U005 | B6: Bar Residence | C6: Pakinkg | D6: A-16 | E6: 6 | F6: 55 | G6: Sold
A7: U006 | B7: Budva Residence | C7: Apartment | D7: A-17 | E7: 7 | F7: 100 | G7: Sold
A8: U007 | B8: Budva Residence | C8: Commercial | D8: A-18 | E8: 9 | F8: 45 | G8: Sold
A9: U008 | B9: Budva Residence | C9: Apartment | D9: A-19 | E9: 2 | F9: 76 | G9: Available
A10: U009 | B10: Bar Residence | C10: Apartment | D10: A-20 | E10: 1 | F10: 34 | G10: Available
A11: U010 | B11: Budva Residence | C11: Apartment | D11: A-21 | E11: 3 | F11: 65 | G11: Sold
A12: U011 | B12: Budva Residence | C12: Apartment | D12: A-22 | E12: 3 | F12: 65 | G12: Sold
A13: U012 | B13: Bar Residence | C13: Pakinkg | D13: A-23 | E13: 3 | F13: 56 | G13: Reserved
... A19: U018 | B19: Bar Residence | C19: Apartment | D19: A-29 | E19: 3 | F19: 65 | G19: Sold

Sheet Clients
A1: Client ID | B1: Name | C1: Phone | D1: Email | E1: Notes
A2: C001 | B2: Agne Durakovic | C2: +382... | D2: email@mail.com
A3: C002 | B3: Alexabder Sagalovic | C3: +382... | D3: email@mail.com
A4: C003 | B4: Alexander Sagalovich | C4: +382... | D4: email@mail.com
A5: C004 | B5: Amar I Mersudin Prentic | C5: +382... | D5: email@mail.com
A6: C005 | B6: Amir Bajramovic | C6: +382... | D6: email@mail.com
A7: C006 | B7: Anastazija Glavicic | C7: +382... | D7: email@mail.com
A8: C007 | B8: Avdulah Destanovic | C8: +382... | D8: email@mail.com
A9: C008 | B9: Balic Esad | C9: +382... | D9: email@mail.com
A10: C009 | B10: Biljana Djikanovic Milic | C10: +382... | D10: email@mail.com
A11: C010 | B11: Bogavac Aleksandra | C11: +382... | D11: email@mail.com
A12: C011 | B12: Bojadžić Sead | C12: +382... | D12: email@mail.com
A13: C012 | B13: Branimir Lakicevic | C13: +382... | D13: email@mail.com
... A15: C014 | B15: Bulatovic Sinisa | C15: +382... | D15: email@mail.com

Sheet Sales
A1: Sale ID | B1: Client ID | C1: Project ID | D1: Unit ID | E1: Price | F1: Price m2 | G1: Reserve Date | H1: Contract Date | I1: Status | J1: Trello | K1: Column 1 | L1: Column 2 | M1: Column 3 | N1: Column 4 | O1: Column 5 | P1: Column 6 | Q1: Column 7 | R1: Column 8
A2: S001 | B2: C001 | C2: P001 | D2: U001 | E2: 1200000 | F2: 2000 | G2: 45992 | H2: 45992 | I2: Signed
A3: S002 | B3: C002 | C3: P001 | D3: U002 | E3: 950000 | F3: 1900 | G3: 45996 | H3: 45996 | I3: Signed
A4: S003 | B4: C003 | C4: P001 | D4: U003 | E4: 1500000 | F4: 2100 | G4: 46032 | H4: 46032 | I4: Signed
A5: S004 | B5: C004 | C5: P002 | D5: U010 | E5: 1100000 | F5: 1800 | G5: 46054 | H5: 46054 | I5: Signed
A6: S005 | B6: C005 | C6: P002 | D6: U011 | E6: 1300000 | F6: 2000 | G6: 46068 | H6: 46068 | I6: Signed
A7: S006
A8: S007
A9: S008
A10: S009
A11: S010
A12: S011
A13: S012
A14: S013
A15: S014
A16: S015
A17: S016
A18: S017
... A20: S019

Sheet Payment Allocations
A1: Payment ID | B1: Sale ID | C1: Client | D1: Allocated | E1: Date
A2: P001 | B2: S001 | C2: C001 | D2: 1200000 | E2: 46064
A3: P002 | B3: S002 | C3: C002 | D3: 950000 | E3: 46065
A4: P005 | B4: S004 | C4: C004 | D4: 1100000 | E4: 46117
A5: P007 | B5: S003 | C5: C003 | D5: 1000000 | E5: 46093
A6: P012 | B6: S003 | C6: C003 | D6: 500000 | E6: 46063

Sheet Client Payments
A1: Payment ID | B1: Date | C1: Client | D1: Unit | E1: Payment Info | F1: Amount | G1: Method | H1: Reference | I1: Confirmed
A2: P001 | B2: 46064 | C2: C001 | D2: U002 | E2: =CONCATENATE(LEFT(VLOOKUP(C2, Clients!$A$2:$B$14, 2, FALSE)& REPT(" ", 20), 20) , " [",VLOOKUP(D2, Units!$A$2:$B$14, 2, FALSE),"]") -> Agne Durakovic [Budva Residence] | F2: 10000000 | G2: Bank | I2: Yes
A3: P002 | B3: 46065 | C3: C002 | D3: U001 | E3: =CONCATENATE(LEFT(VLOOKUP(C3, Clients!$A$2:$B$14, 2, FALSE)& REPT(" ", 20), 20) , " [",VLOOKUP(D3, Units!$A$2:$B$14, 2, FALSE),"]") -> Alexabder Sagalovic [Budva Residence] | F3: 20000000 | G3: Bank | I3: Yes
A4: P003 | B4: 46071 | C4: C001 | D4: U004 | E4: =CONCATENATE(LEFT(VLOOKUP(C4, Clients!$A$2:$B$14, 2, FALSE)& REPT(" ", 20), 20) , " [",VLOOKUP(D4, Units!$A$2:$B$14, 2, FALSE),"]") -> Agne Durakovic [Ulcin Residence] | F4: 3000000 | G4: Bank | I4: Yes
A5: P004 | B5: 46116 | C5: C002 | D5: U005 | E5: =CONCATENATE(LEFT(VLOOKUP(C5, Clients!$A$2:$B$14, 2, FALSE)& REPT(" ", 20), 20) , " [",VLOOKUP(D5, Units!$A$2:$B$14, 2, FALSE),"]") -> Alexabder Sagalovic [Bar Residence] | F5: 1000000 | G5: Bank | I5: Yes | J5: payment example
A6: P005 | B6: 46117 | C6: C004 | D6: U005 | E6: =CONCATENATE(LEFT(VLOOKUP(C6, Clients!$A$2:$B$14, 2, FALSE)& REPT(" ", 20), 20) , " [",VLOOKUP(D6, Units!$A$2:$B$14, 2, FALSE),"]") -> Amar I Mersudin Pren [Bar Residence] | F6: 2000000 | G6: Bank | I6: Yes
A7: P006 | B7: 46118 | C7: C006 | D7: U006 | E7: =CONCATENATE(LEFT(VLOOKUP(C7, Clients!$A$2:$B$14, 2, FALSE)& REPT(" ", 20), 20) , " [",VLOOKUP(D7, Units!$A$2:$B$14, 2, FALSE),"]") -> Anastazija Glavicic [Budva Residence] | F7: 3000000 | G7: Bank | I7: Yes
A8: P007 | B8: 46093 | C8: C003 | D8: U010 | E8: =CONCATENATE(LEFT(VLOOKUP(C8, Clients!$A$2:$B$14, 2, FALSE)& REPT(" ", 20), 20) , " [",VLOOKUP(D8, Units!$A$2:$B$14, 2, FALSE),"]") -> Alexander Sagalovich [Budva Residence] | F8: 1000000 | G8: Bank | I8: Yes
A9: P008 | B9: 46120 | C9: C001 | D9: U003 | E9: =CONCATENATE(LEFT(VLOOKUP(C9, Clients!$A$2:$B$14, 2, FALSE)& REPT(" ", 20), 20) , " [",VLOOKUP(D9, Units!$A$2:$B$14, 2, FALSE),"]") -> Agne Durakovic [Budva Residence] | F9: 1500000 | G9: Bank | I9: Yes
A10: P009 | B10: 46065 | C10: C004 | D10: U006 | E10: =CONCATENATE(LEFT(VLOOKUP(C10, Clients!$A$2:$B$14, 2, FALSE)& REPT(" ", 20), 20) , " [",VLOOKUP(D10, Units!$A$2:$B$14, 2, FALSE),"]") -> Amar I Mersudin Pren [Budva Residence] | F10: 1000000 | G10: Bank | I10: Yes
A11: P010 | B11: 46122 | C11: C004 | D11: U001 | E11: =CONCATENATE(LEFT(VLOOKUP(C11, Clients!$A$2:$B$14, 2, FALSE)& REPT(" ", 20), 20) , " [",VLOOKUP(D11, Units!$A$2:$B$14, 2, FALSE),"]") -> Amar I Mersudin Pren [Budva Residence] | F11: 1500000 | G11: Bank | I11: Yes
A12: P011 | B12: 46123 | C12: C001 | D12: U002 | E12: =CONCATENATE(LEFT(VLOOKUP(C12, Clients!$A$2:$B$14, 2, FALSE)& REPT(" ", 20), 20) , " [",VLOOKUP(D12, Units!$A$2:$B$14, 2, FALSE),"]") -> Agne Durakovic [Budva Residence] | F12: 1000000 | G12: Bank | I12: Yes
A13: P012 | B13: 46063 | C13: C003 | D13: U003 | E13: =CONCATENATE(LEFT(VLOOKUP(C13, Clients!$A$2:$B$14, 2, FALSE)& REPT(" ", 20), 20) , " [",VLOOKUP(D13, Units!$A$2:$B$14, 2, FALSE),"]") -> Alexander Sagalovich [Budva Residence] | F13: 2000000 | G13: Bank | I13: Yes
A14: P013 | B14: 46125 | C14: C003 | D14: U004 | E14: =CONCATENATE(LEFT(VLOOKUP(C14, Clients!$A$2:$B$14, 2, FALSE)& REPT(" ", 20), 20) , " [",VLOOKUP(D14, Units!$A$2:$B$14, 2, FALSE),"]") -> Alexander Sagalovich [Ulcin Residence] | F14: 3000000 | G14: Bank | I14: Yes
A15: P014 | B15: 46037 | C15: C001 | D15: U003 | E15: =CONCATENATE(LEFT(VLOOKUP(C15, Clients!$A$2:$B$14, 2, FALSE)& REPT(" ", 20), 20) , " [",VLOOKUP(D15, Units!$A$2:$B$14, 2, FALSE),"]") -> Agne Durakovic [Budva Residence] | F15: 10000000 | G15: Bank | I15: Yes
A16: P015 | B16: 45994 | C16: C008 | D16: U013 | E16: =CONCATENATE(LEFT(VLOOKUP(C16, Clients!$A$2:$B$14, 2, FALSE)& REPT(" ", 20), 20) , " [",VLOOKUP(D16, Units!$A$2:$B$14, 2, FALSE),"]") -> Balic Esad [Ulcin Residence] | F16: 15000000 | G16: Bank | I16: Yes
I146: FALSE
I147: FALSE
I148: FALSE
I149: FALSE
I150: FALSE
I151: FALSE
I152: FALSE
I153: FALSE
I154: FALSE
I155: FALSE
I156: FALSE
I157: FALSE
... I1003: FALSE

Sheet Budget
A1: Budget ID | B1: Project | C1: Category | D1: Unit | E1: Qty | F1: Price | G1: Total (Estimated) | H1: Total (Real) | I1: Difference
A2: B001 | B2: P001 | C2: I PRIPREMNI RADOVI | D2: m3 | E2: 400 | F2: 120 | G2: 29474 | H2: 30000 | I2: =G2-H2 -> -526
A3: B002 | B3: P001 | C3: II ZEMLJANI RADOVI | G3: 281551.97 | H3: 295555 | I3: =G3-H3 -> -14003.028
A4: B003 | B4: P001 | C4: III BETONSKI I ARM. BETONSKI RADOVI | G4: 1662203.3 | H4: 1500000 | I4: =G4-H4 -> 162203.3
A5: B004 | B5: P001 | C5: IV ARMIRAČKI RADOVI | G5: 1465972.3 | H5: 1465972.3 | I5: =G5-H5 -> 0 | K5: ESTIMATED | L5: REAL | M5: BALANCE
A6: B005 | B6: P001 | C6: V ČELIČNI RADOVI | G6: 3798.16 | H6: 3700.8437 | I6: =G6-H6 -> 97.316347 | K6: =SUM(Budjet[Total (Estimated)]) -> 8853393 | L6: =SUM(Budjet[Total (Real)]) -> 8678212.3 | M6: =K6-L6 -> 175180.7
A7: B006 | B7: P001 | C7: VI ZIDARSKI RADOVI | G7: 887552.61 | H7: 876679.46 | I7: =G7-H7 -> 10873.15
A8: B007 | B8: P001 | C8: VII IZOLATERSKI RADOVI | G8: 462255.94 | H8: 443925.56 | I8: =G8-H8 -> 18330.376
A9: B008 | B9: P001 | C9: VIII FASADNA BRAVARIJA | G9: 372880 | H9: 373892.16 | I9: =G9-H9 -> -1012.1647
A10: B009 | B10: P001 | C10: IX BRAVARSKI RADOVI | G10: 505675 | H10: 489000.74 | I10: =G10-H10 -> 16674.263
A11: B010 | B11: P001 | C11: X STOLARSKI RADOVI | G11: 84100 | H11: 84683.475 | I11: =G11-H11 -> -583.47456
A12: B011 | B12: P001 | C12: XI LIMARSKI RADOVI | G12: 56612.5 | H12: 55542.434 | I12: =G12-H12 -> 1070.0665
A13: B012 | B13: P001 | C13: XII PODOPOLAGAČKI RADOVI | G13: 366640 | H13: 371751.53 | I13: =G13-H13 -> -5111.5273
A14: B013 | B14: P001 | C14: XIII KERAMIČARSKI RADOVI | G14: 162493 | H14: 165943.36 | I14: =G14-H14 -> -3450.3604
A15: B014 | B15: P001 | C15: XIV KAMENOPOLAGAČKI RADOVI | G15: 103905.01 | H15: 102646.13 | I15: =G15-H15 -> 1258.8847
A16: B015 | B16: P001 | C16: XV FASADERSKI RADOVI | G16: 133551.87 | H16: 132582.17 | I16: =G16-H16 -> 969.69431
A17: B016 | B17: P001 | C17: XVI SUVOMONTAŽNI RADOVI | G17: 289779.3 | H17: 303043.79 | I17: =G17-H17 -> -13264.489
A18: B017 | B18: P001 | C18: XVII MOLERSKO-FARBARSKI RADOVI | G18: 282510.94 | H18: 276265.69 | I18: =G18-H18 -> 6245.2543
... A30: B029 | B30: P001 | C30: XXIX VODOVOD I KANALIZACIJA | G30: 12333 | H30: 12082.901 | I30: =G30-H30 -> 250.09892

Sheet Contractors
A1: Contractor ID | B1: Name | C1: Phone | D1: Email | E1: Notes | F1: Column 1 | G1: Column 2
A2: CTR1 | B2: Дима | C2: 911 | D2: some@gmail.com | E2: Дима
A3: CTR2 | B3: Слава | C3: 911 | D3: some@gmail.com
A4: CTR3 | B4: Мага | C4: 911 | D4: some@gmail.com

Sheet Contracts
A1: Contract ID | B1: Project ID | C1: Contractor Name | D1: Contract Name | E1: Contract Amount | F1: Paid | G1: Remaining | H1: % Complete | I1: Status | J1: Trello
A2: D1 | B2: CTR1 | C2: =VLOOKUP(B2, Contractors!$A$2:$B$17, 2, FALSE) -> Дима | D2: Rough works | E2: 100000 | F2: 400000 | G2: -300000 | H2: 4 | I2: Completed
A3: D2 | B3: CTR2 | C3: =VLOOKUP(B3, Contractors!$A$2:$B$17, 2, FALSE) -> Слава | D3: Electrics | E3: 120000 | F3: 100000 | G3: 20000 | H3: 0.83333333 | I3: Active
A4: D3 | B4: CTR3 | C4: =VLOOKUP(B4, Contractors!$A$2:$B$17, 2, FALSE) -> Мага | D4: Facade | E4: 150000 | F4: 100000 | G4: 50000 | H4: 0.66666667 | I4: Active
A5: D4 | B5: CTR1 | C5: =VLOOKUP(B5, Contractors!$A$2:$B$17, 2, FALSE) -> Дима | D5: Electrics | E5: 100000 | F5: 100000 | G5: 0 | H5: 1 | I5: Completed
A6: D5 | C6: =VLOOKUP(B6, Contractors!$A$2:$B$17, 2, FALSE) -> #N/A | F6: 0 | G6: 0 | H6: 0 | I6: Active
A7: D6 | C7: =VLOOKUP(B7, Contractors!$A$2:$B$17, 2, FALSE) -> #N/A | F7: 0 | G7: 0 | H7: 0 | I7: Active
A8: D7 | C8: =VLOOKUP(B8, Contractors!$A$2:$B$17, 2, FALSE) -> #N/A | F8: 0 | G8: 0 | H8: 0 | I8: Active
A9: D8 | C9: =VLOOKUP(B9, Contractors!$A$2:$B$17, 2, FALSE) -> #N/A | F9: 0 | G9: 0 | H9: 0 | I9: Active
A10: D9 | C10: =VLOOKUP(B10, Contractors!$A$2:$B$17, 2, FALSE) -> #N/A | F10: 0 | G10: 0 | H10: 0 | I10: Active
A11: D10 | C11: =VLOOKUP(B11, Contractors!$A$2:$B$17, 2, FALSE) -> #N/A | F11: 0 | G11: 0 | H11: 0 | I11: Active
A12: D11 | C12: =VLOOKUP(B12, Contractors!$A$2:$B$17, 2, FALSE) -> #N/A | F12: 0 | G12: 0 | H12: 0 | I12: Active
A13: D12 | C13: =VLOOKUP(B13, Contractors!$A$2:$B$17, 2, FALSE) -> #N/A | F13: 0 | G13: 0 | H13: 0 | I13: Active
A14: D13 | C14: =VLOOKUP(B14, Contractors!$A$2:$B$17, 2, FALSE) -> #N/A | F14: 0 | G14: 0 | H14: 0 | I14: Active
A15: D14 | C15: =VLOOKUP(B15, Contractors!$A$2:$B$17, 2, FALSE) -> #N/A | F15: 0 | G15: 0 | H15: 0 | I15: Active
A16: D15 | C16: =VLOOKUP(B16, Contractors!$A$2:$B$17, 2, FALSE) -> #N/A | F16: 0 | G16: 0 | H16: 0 | I16: Active
F17: 0 | G17: 0 | H17: 0 | I17: Active
F18: 0 | G18: 0 | H18: 0 | I18: Active

Sheet Expenses
A1: Expense ID | B1: Date | C1: Project | D1: Contractor | E1: Contract | F1: Category | G1: Amount | H1: Status | I1: Payment Date | J1: Verification
A2: EX1 | B2: 46133 | C2: P001 | D2: CTR1 | E2: D1 | F2: II ZEMLJANI RADOVI | G2: 100000 | H2: Paid | I2: 46065 | J2: Verified
A3: EX2 | B3: 46134 | C3: P002 | D3: CTR2 | E3: D2 | F3: III BETONSKI I ARM. BETONSKI RADOVI | G3: 100000 | H3: Paid | I3: 46084 | J3: Verified
A4: EX3 | B4: 46135 | C4: P001 | D4: CTR1 | E4: D1 | F4: II ZEMLJANI RADOVI | G4: 200000 | H4: Paid | I4: 46065 | J4: Verified
A5: EX4 | B5: 46136 | C5: P001 | D5: CTR1 | E5: D1 | F5: I PRIPREMNI RADOVI | G5: 100000 | H5: Paid | I5: 46129 | J5: Verified
A6: EX5 | B6: =TODAY() -> 46146 | C6: P002 | D6: CTR3 | E6: D3 | F6: VI ZIDARSKI RADOVI | G6: 100000 | H6: Paid | I6: 46131 | J6: Verified
A7: EX6 | B7: =TODAY() -> 46146 | C7: P001 | D7: CTR3 | E7: D4 | F7: I PRIPREMNI RADOVI | G7: 100000 | H7: Paid | I7: 46132 | J7: Verified
J8: FALSE
J9: FALSE
J10: FALSE
J11: FALSE
J12: FALSE
J13: FALSE
J14: FALSE
J15: FALSE
J16: FALSE
J17: FALSE
J18: FALSE
J19: FALSE
... J27: FALSE

Sheet Receivables
A1: Client | B1: Project | C1: Unit | D1: Sale | E1: Paid | F1: Outstanding | G1: Status | H1: Column 8
A2: C001 | B2: P001 | C2: U001 | D2: 1200000 | E2: 25500000 | F2: -24300000 | G2: Paid
A3: C002 | B3: P001 | C3: U002 | D3: 950000 | E3: 21000000 | F3: -20050000 | G3: Paid
A4: C003 | B4: P001 | C4: U003 | D4: 1500000 | E4: 6000000 | F4: -4500000 | G4: Paid
A5: C004 | B5: P002 | C5: U010 | D5: 1100000 | E5: 4500000 | F5: -3400000 | G5: Paid
A6: C005 | B6: P002 | C6: U011 | D6: 1300000 | E6: 0 | F6: 1300000 | G6: Unpaid

Sheet Bank Accounts
A1: Account ID | B1: Name | C1: Bank | D1: Currency | E1: Balance | F1: Updated
A2: ACC001 | B2: Main Account | C2: CKB | D2: EUR | E2: 350000 | F2: 01.04.2026

Sheet Cash Flow
A1: Month | B1: Opening | C1: Income | D1: Expense | E1: Net | F1: Closing | G1: Verifying
A2: 45992 | B2: 0 | C2: 15000000 | D2: 0 | E2: 15000000 | F2: 15000000 | G2: TRUE
A3: 46023 | B3: 15000000 | C3: 10000000 | D3: 0 | E3: 10000000 | F3: 25000000 | G3: TRUE
A4: 46054 | B4: 25000000 | C4: 36000000 | D4: 300000 | E4: 35700000 | F4: 60700000 | G4: TRUE
A5: 46082 | B5: 60700000 | C5: 1000000 | D5: 100000 | E5: 900000 | F5: 61600000 | G5: TRUE
A6: 46113 | B6: 61600000 | C6: 13000000 | D6: 300000 | E6: 12700000 | F6: 74300000 | G6: TRUE

Sheet VAT
A1: Month | B1: Project ID | C1: Incoming VAT | D1: Outgoing VAT | E1: VAT Payable | F1: Cumulative VAT | G1: Type
A2: 45992 | B2: C008 | C2: 0 | D2: 2603305.8 | E2: 2603305.8 | F2: 2603305.8 | G2: Payable
A3: 46023 | B3: C001 | C3: 0 | D3: 1735537.2 | E3: 1735537.2 | F3: 4338843 | G3: Payable
A4: 46054 | B4: P001 | C4: 52066.116 | D4: 0 | E4: -52066.116 | F4: 4286776.9 | G4: Refund
A5: 46054 | B5: C001 | C5: 0 | D5: 2256198.3 | E5: 2256198.3 | F5: 6542975.2 | G5: Payable
A6: 46054 | B6: C002 | C6: 0 | D6: 3471074.4 | E6: 3471074.4 | F6: 10014050 | G6: Payable
A7: 46054 | B7: C004 | C7: 0 | D7: 173553.72 | E7: 173553.72 | F7: 10187603 | G7: Payable
A8: 46054 | B8: C003 | C8: 0 | D8: 347107.44 | E8: 347107.44 | F8: 10534711 | G8: Payable
A9: 46082 | B9: P002 | C9: 17355.372 | D9: 0 | E9: -17355.372 | F9: 10517355 | G9: Refund
A10: 46082 | B10: C003 | C10: 0 | D10: 173553.72 | E10: 173553.72 | F10: 10690909 | G10: Payable
A11: 46113 | B11: P001 | C11: 34710.744 | D11: 0 | E11: -34710.744 | F11: 10656198 | G11: Refund
A12: 46113 | B12: P002 | C12: 17355.372 | D12: 0 | E12: -17355.372 | F12: 10638843 | G12: Refund
A13: 46113 | B13: C002 | C13: 0 | D13: 173553.72 | E13: 173553.72 | F13: 10812397 | G13: Payable
... A17: 46113 | B17: C003 | C17: 0 | D17: 520661.16 | E17: 520661.16 | F17: 12895041 | G17: Payable

Sheet Dashboard
A1: PROJECT OVERVIEW
A2: Total Projects | B2: 3
A3: Active Projects | B3: 2
A4: Completed Projects | B4: 0
A6: SALES & CLIENTS
A7: Total Sales Value | B7: 6050000
A8: Received from Clients | B8: 75000000
A9: Outstanding | B9: -68950000
F10: Sales → сколько продали (Revenue)
A11: EXPENSES & CONTRACTS | F11: Payments → сколько получили (Cash)
A12: Total Budget | B12: 8678212.3 | F12: Expenses → сколько потратили
A13: Contracted Amount | B13: 470000 | F13: Bank → сколько денег сейчас
A14: Paid to Contractors | B14: 700000
A15: Remaining Budget | B15: 7978212.3
A17: CASH POSITION
A18: Total Cash | B18: 350000
A19: Receivables | B19: 75000000
A20: Payables | B20: 700000
A21: Net Cash | B21: 350000
A23: PROFITABILITY
A24: Revenue | B24: 6050000
A25: Expenses | B25: 700000
A26: Profit | B26: 5350000
A27: ROI | B27: 0.60329274
A29: VAT OVERVIEW
A30: Current VAT Payable | B30: 121487.6
A31: Total Incoming VAT | B31: 13016529
A32: Total Outgoing VAT | B32: 12895041
A33: Cumulative VAT | B33: 470000
B34: 700000
B35: -230000
B36: 0.05415862
